area_weighted_join/__init__.py
area_weighted_join/area_weighted_join.py
area_weighted_join-0.1.dist-info/METADATA
area_weighted_join-0.1.dist-info/RECORD
area_weighted_join-0.1.dist-info/WHEEL
area_weighted_join-0.1.dist-info/top_level.txt
