Metadata-Version: 2.1
Name: area-weighted-join
Version: 0.1
Summary: Spatially join misaligned polygons
Home-page: http://github.com/azavea/area-weighted-join
Author: Simon Kassel
Author-email: skassel@azavea.com
License: UNKNOWN
Platform: UNKNOWN
Classifier: Programming Language :: Python :: 3
Classifier: License :: OSI Approved :: MIT License
Classifier: Operating System :: OS Independent
